pynuml/__init__.py
pynuml/meta.yaml
pynuml/data/__init__.py
pynuml/data/nugraph_data.py
pynuml/io/__init__.py
pynuml/io/file.py
pynuml/io/h5interface.py
pynuml/io/out.py
pynuml/labels/__init__.py
pynuml/labels/ccqe.py
pynuml/labels/flavor.py
pynuml/labels/pdk.py
pynuml/labels/simple.py
pynuml/labels/standard.py
pynuml/plot/__init__.py
pynuml/plot/graph.py
pynuml/process/__init__.py
pynuml/process/base.py
pynuml/process/hitgraph.py
pynuml/process/spmap.py
pynuml-25.4.0.dist-info/licenses/LICENSE
pynuml-25.4.0.dist-info/WHEEL
pynuml-25.4.0.dist-info/METADATA
pynuml-25.4.0.dist-info/RECORD
