Metadata-Version: 2.4
Name: pynuml
Version: 25.4.0
Summary: Standardised ML input processing for particle physics
Author-email: v hewes <vhewes@fnal.gov>
Requires-Python: >=3.7
Classifier: Intended Audience :: Science/Research
Classifier: License :: OSI Approved :: MIT License
License-File: LICENSE
Requires-Dist: h5py>=3.7.0
Requires-Dist: mpi4py
Requires-Dist: pandas
Requires-Dist: particle
Requires-Dist: plotly
Requires-Dist: scikit-learn
Requires-Dist: torch>=1.12.1
Requires-Dist: torch-geometric>=2.1.0
Project-URL: Home, https://github.com/nugraph/pynuml
